LICENSE.txt
README.md
setup.cfg
setup.py
joyeuse/__init__.py
joyeuse/__main__.py
joyeuse/__version__.py
joyeuse.egg-info/PKG-INFO
joyeuse.egg-info/SOURCES.txt
joyeuse.egg-info/dependency_links.txt
joyeuse.egg-info/entry_points.txt
joyeuse.egg-info/requires.txt
joyeuse.egg-info/top_level.txt
joyeuse/cube/__init__.py
joyeuse/cube/cube.py
joyeuse/misc/__init__.py
joyeuse/misc/compat.py
joyeuse/misc/log.py
joyeuse/settings/__init__.py
joyeuse/settings/item.py
joyeuse/settings/parameter.py
joyeuse/settings/section.py
joyeuse/settings/settings.py
joyeuse/settings/sub_section.py
joyeuse/ui/__init__.py
joyeuse/ui/input_validation.py
joyeuse/ui/main_window.py