Metadata-Version: 2.1
Name: joyeuse
Version: 0.1.0
Summary: Configuration tool for the joyeuse storyteller
Home-page: https://github.com/ncarrier/joyeuse
Author: Nicolas Carrier
Author-email: carrier.nicolas0@gmail.com
License: GPLv3+
Classifier: Development Status :: 2 - Pre-Alpha
Classifier: Environment :: X11 Applications
Classifier: Intended Audience :: End Users/Desktop
Classifier: License :: OSI Approved :: GNU General Public License v3 or later (GPLv3+)
Classifier: Topic :: Other/Nonlisted Topic
Classifier: Programming Language :: Python
Classifier: Programming Language :: Python :: 3 :: Only
Requires-Python: >=3.6.0
License-File: LICENSE.txt
